tootlogger/__init__.py
tootlogger/cli.py
tootlogger/templates/template.jinja2
tootlogger-0.4.4.dist-info/WHEEL
tootlogger-0.4.4.dist-info/entry_points.txt
tootlogger-0.4.4.dist-info/LICENSE.txt
tootlogger-0.4.4.dist-info/METADATA
tootlogger-0.4.4.dist-info/RECORD
