Metadata-Version: 2.1
Name: tootlogger
Version: 0.4.4
Summary: Log your Mastodon toots to DayOne
Home-page: https://github.com/onlyhavecans/tootlogger
License: BSD
Keywords: social media,mastodon
Author: Amelia Aronsohn
Author-email: squirrel@wearing.black
Requires-Python: >=3.11,<4.0
Classifier: Environment :: Console
Classifier: Intended Audience :: End Users/Desktop
Classifier: License :: Other/Proprietary License
Classifier: Natural Language :: English
Classifier: Operating System :: MacOS :: MacOS X
Classifier: Programming Language :: Python :: 3
Classifier: Programming Language :: Python :: 3.11
Classifier: Topic :: Utilities
Requires-Dist: Jinja2 (>=3.1.2,<4.0.0)
Requires-Dist: html2text (>=2020.1.16,<2021.0.0)
Requires-Dist: mastodon.py (>=1.6,<2.0)
Requires-Dist: toml (>=0.10.2,<0.11.0)
Project-URL: Repository, https://github.com/onlyhavecans/tootlogger
